Verilog/Combinational/ALU/main.v
/*
 * Example Arithmetic Logic Unit 8 operations
 *
 * opr == b000 => s = a + b 
 * opr == b001 => s = a - b 
 * opr == b010 => s = a << b 
 * opr == b011 => s = a >> b 
 * opr == b100 => s = a & b 
 * opr == b101 => s = a | b 
 * opr == b110 => s = a ^ b 
 * opr == b111 => s = ~a 
 *  
 */
`default_nettype none
module alu(opr, a, b, s);
    input [2:0] opr;
    input [3:0] a, b;
    output [3:0] s;

    assign s = opr == 3'b000 ? a + b :
               opr == 3'b001 ? a - b :
               opr == 3'b010 ? a << b :
               opr == 3'b011 ? a >> b :
               opr == 3'b100 ? a & b :
               opr == 3'b101 ? a | b :
               opr == 3'b110 ? a ^ b :
               ~a;
endmodule

Combinational/ALU/tb.v
module main_tb;
    reg [3:0] a, b;
    reg [2:0] opr;
    wire [3:0] s;

    alu uut(.a(a), .b(b), .opr(opr), .s(s));

    initial begin
        $dumpfile("main.vcd");
        $dumpvars(0, main_tb);
    end
    
    initial begin
        $monitor("A=%b B=%b OPR=%b S=%d Time=%0dns", a, b, opr, s, $time);

        opr = 3'b000;
        a = 4'd10; b = 4'd5;
        #10;

        opr = 3'b001;
        #10;

        opr = 3'b010;
        a = 4'd10; b = 4'd2;
        #10;
        
        opr = 3'b011;
        #10;

        opr = 3'b100;
        a = 4'd9; b = 4'd7;
        #10;
        
        opr = 3'b101;
        #10;

        opr = 3'b110;
        #10;

        opr = 3'b111;
        a = 4'b1111;
        #10;

        $finish;
    end

endmodule

Combinational/ALU/main.vcd
$date
	Mon Jun 29 21:17:04 2026
$end
$version
	Icarus Verilog
$end
$timescale
	1s
$end
$scope module main_tb $end
$var wire 4 ! s [3:0] $end
$var reg 4 " a [3:0] $end
$var reg 4 # b [3:0] $end
$var reg 3 $ opr [2:0] $end
$scope module uut $end
$var wire 4 % a [3:0] $end
$var wire 4 & b [3:0] $end
$var wire 3 ' opr [2:0] $end
$var wire 4 ( s [3:0] $end
$upscope $end
$upscope $end
$enddefinitions $end
$comment Show the parameter values. $end
$dumpall
$end
#0
$dumpvars
b1111 (
b0 '
b101 &
b1010 %
b0 $
b101 #
b1010 "
b1111 !
$end
#10
b101 !
b101 (
b1 $
b1 '
#20
b1000 !
b1000 (
b10 #
b10 &
b10 $
b10 '
#30
b10 !
b10 (
b11 $
b11 '
#40
b1 !
b1 (
b111 #
b111 &
b1001 "
b1001 %
b100 $
b100 '
#50
b1111 !
b1111 (
b101 $
b101 '
#60
b1110 !
b1110 (
b110 $
b110 '
#70
b0 !
b0 (
b1111 "
b1111 %
b111 $
b111 '
