Sequential/ShiftRegister/main.v
module shiftreg(clr, ld, left, right, d, q);
    input clr, ld, left, right;
    input [3:0] d;
    output reg [3:0] q;

    initial begin
        q = 4'b0000;
    end

    always @* begin
        casex ({clr, ld, left, right})
            4'b1xxx: q = 4'b0000;    // Clear
            4'b01xx: q = d;          // Load
            4'b001x: q = q << 1;     // Shift left
            4'b0001: q = q >> 1;     // Shift right
            default: q = q;          // Hold
        endcase
    end
endmodule

Verilog/Sequential/ShiftRegister/tb.v
module main_tb;

    reg clr, ld, left, right;
    reg [3:0] d;
    wire [3:0] q;

    shiftreg uut (.clr(clr), .ld(ld), .left(left), .right(right), .d(d), .q(q));

    initial begin
        $dumpfile("main.vcd");
        $dumpvars(0, main_tb);
    end
    
    initial begin
        clr = 0; ld = 0; left = 0; right = 0; d = 4'b0000;
        // Test clear
        #10 clr = 1; #10 clr = 0;
        // Test load
        #10 ld = 1; d = 4'b1010; #10 ld = 0;
        // Test shift left
        #10 left = 1; #10 left = 0;
        // Test shift right
        #10 right = 1; #10 right = 0;
        // Test hold
        #10;
        $finish;
    end
endmodule

Verilog/Sequential/ShiftRegister/main.vcd
$date
	Wed Jul  1 10:17:48 2026
$end
$version
	Icarus Verilog
$end
$timescale
	1s
$end
$scope module main_tb $end
$var wire 4 ! q [3:0] $end
$var reg 1 " clr $end
$var reg 4 # d [3:0] $end
$var reg 1 $ ld $end
$var reg 1 % left $end
$var reg 1 & right $end
$scope module uut $end
$var wire 1 " clr $end
$var wire 4 ' d [3:0] $end
$var wire 1 $ ld $end
$var wire 1 % left $end
$var wire 1 & right $end
$var reg 4 ( q [3:0] $end
$upscope $end
$upscope $end
$enddefinitions $end
#0
$dumpvars
b0 (
b0 '
0&
0%
0$
b0 #
0"
b0 !
$end
#10
1"
#20
0"
#30
b1010 !
b1010 (
b1010 #
b1010 '
1$
#40
0$
#50
b100 !
b100 (
1%
#60
0%
#70
b10 !
b10 (
1&
#80
0&
