Combinational/ParityGenEven/main.v
`default_nettype none
module paritygeneven(a0, a1, a2, a3, p);
    input a0, a1, a2, a3;
    output p;

    assign p = a0 ^ a1 ^ a2 ^ a3;

endmodule

Combinational/ParityGenEven/tb.v
module main_tb;

    reg a0, a1, a2, a3;
    wire p;

    paritygeneven uut(.a0(a0), .a1(a1), .a2(a2), .a3(a3), .p(p));

    initial begin
        $dumpfile("main.vcd");
        $dumpvars(0, main_tb);
    end
    
    initial begin
        $monitor("A0=%d | A1=%d | A2=%d | A3=%d | P=%d | Time%0dns", a0, a1, a2, a3, p, $time);

        a0=1'b0; a1=1'b0; a2=1'b0; a3='b0;
        #10
        a0=1'b1; a1=1'b0; a2=1'b0; a3='b0;
        #10
        a0=1'b0; a1=1'b1; a2=1'b0; a3='b0;
        #10
        a0=1'b1; a1=1'b1; a2=1'b0; a3='b0;
        #10
        a0=1'b0; a1=1'b0; a2=1'b1; a3='b0;
        #10
        a0=1'b1; a1=1'b0; a2=1'b1; a3='b0;
        #10
        a0=1'b1; a1=1'b1; a2=1'b0; a3='b0;
        #10
        a0=1'b1; a1=1'b1; a2=1'b1; a3='b0;
        #10
        a0=1'b0; a1=1'b0; a2=1'b0; a3='b1;
        #10
        a0=1'b1; a1=1'b0; a2=1'b0; a3='b1;
        #10
        a0=1'b0; a1=1'b1; a2=1'b0; a3='b1;
        #10
        a0=1'b1; a1=1'b1; a2=1'b0; a3='b1;
        #10
        a0=1'b0; a1=1'b0; a2=1'b1; a3='b1;
        #10
        a0=1'b1; a1=1'b0; a2=1'b1; a3='b1;
        #10
        a0=1'b0; a1=1'b1; a2=1'b1; a3='b1;
        #10
        a0=1'b1; a1=1'b1; a2=1'b1; a3='b1;
        #10

        $finish;
    end

endmodule

Combinational/ParityGenEven/main.vcd
$date
	Mon Jun 29 11:05:27 2026
$end
$version
	Icarus Verilog
$end
$timescale
	1s
$end
$scope module main_tb $end
$var wire 1 ! p $end
$var reg 1 " a0 $end
$var reg 1 # a1 $end
$var reg 1 $ a2 $end
$var reg 1 % a3 $end
$scope module uut $end
$var wire 1 " a0 $end
$var wire 1 # a1 $end
$var wire 1 $ a2 $end
$var wire 1 % a3 $end
$var wire 1 ! p $end
$upscope $end
$upscope $end
$enddefinitions $end
$comment Show the parameter values. $end
$dumpall
$end
#0
$dumpvars
0%
0$
0#
0"
0!
$end
#10
1!
1"
#20
1#
0"
#30
0!
1"
#40
1!
1$
0#
0"
#50
0!
1"
#60
0$
1#
#70
1!
1$
#80
1%
0$
0#
0"
#90
0!
1"
#100
1#
0"
#110
1!
1"
#120
0!
1$
0#
0"
#130
1!
1"
#140
1#
0"
#150
0!
1"
