Combinational/Summer/main.v
/*
 * Full Summer
 */
module summer(a, b, cin, s, cout);

    input a, b, cin;
    output s, cout;

    wire outOr1, outAnd1, outAnd2;

    xor xor1(outOr1, a, b);
    xor xor2(s, outOr1, cin);
    and and1(outAnd1, outOr1, cin);
    and and2(outAnd2, a, b);
    or or3(cout, outAnd1, outAnd2);

endmodule

Combinational/Summer/tb.v
`timescale 1ns/1ps

module main_tb;

    reg a_tb, b_tb, cin_tb;
    wire outOr1_tb, outAnd1_tb, outAnd2_tb, s_tb, cout_tb;

    summer uut(.a(a_tb), .b(b_tb), .cin(cin_tb), .s(s_tb), .cout(cout_tb));

    initial begin
        $dumpfile("main.vcd");
        $dumpvars(0, main_tb);
    end

    initial begin
    
        a_tb = 0; b_tb = 0; cin_tb = 0;
        #10
        a_tb = 0; b_tb = 0; cin_tb = 1;
        #10
        a_tb = 0; b_tb = 1; cin_tb = 0;
        #10
        a_tb = 0; b_tb = 1; cin_tb = 1;
        #10
        a_tb = 1; b_tb = 0; cin_tb = 0;
        #10
        a_tb = 1; b_tb = 0; cin_tb = 1;
        #10
        a_tb = 1; b_tb = 1; cin_tb = 0;
        #10
        a_tb = 1; b_tb = 1; cin_tb = 1;
        #10
        
    $display("Finish.");
    $finish;
    end

endmodule

Combinational/Summer/main.vcd
$date
	Sat Jun 27 19:01:14 2026
$end
$version
	Icarus Verilog
$end
$timescale
	1ps
$end
$scope module main_tb $end
$var wire 1 ! s_tb $end
$var wire 1 " cout_tb $end
$var reg 1 # a_tb $end
$var reg 1 $ b_tb $end
$var reg 1 % cin_tb $end
$scope module uut $end
$var wire 1 # a $end
$var wire 1 $ b $end
$var wire 1 % cin $end
$var wire 1 " cout $end
$var wire 1 & outAnd1 $end
$var wire 1 ' outAnd2 $end
$var wire 1 ( outOr1 $end
$var wire 1 ! s $end
$upscope $end
$upscope $end
$enddefinitions $end
$comment Show the parameter values. $end
$dumpall
$end
#0
$dumpvars
0(
0'
0&
0%
0$
0#
0"
0!
$end
#10000
1!
1%
#20000
1(
0%
1$
#30000
1"
0!
1&
1%
#40000
0"
1!
0&
0%
0$
1#
#50000
1"
0!
1&
1%
#60000
0&
0(
1'
0%
1$
#70000
1!
1%
