FSM/Accumulator/main.v
`default_nettype none
module fsmaccumulator(clk, rst, x, vlr, tot);
    input clk, rst, x;
    input [7:0] vlr;
    output reg [7:0] tot;
    
    reg [1:0] state;
    localparam START = 2'b00;
    localparam WAIT  = 2'b01;
    localparam SUM   = 2'b10;
    localparam WAIT2 = 2'b11;

    initial begin
        state <= START;
        // tot <= 8'b0;
    end

    always @(posedge clk, negedge rst) begin
        
        if (rst == 1'b0) begin
            tot = 8'b0;
            state <= START;
        end

        case (state)
            START: begin
                tot = 8'b0;
                state <= WAIT;
            end
            WAIT: if (x == 1'b0) state <= SUM;
            SUM: begin
                tot = tot + vlr;
                state <= WAIT2;
            end
            WAIT2: begin
                if (x == 1'b0) state <= WAIT;
            end
        
        endcase
    end

endmodule

Verilog/FSM/Accumulator/tb.v
module main_tb;
    reg clk, rst, x;
    reg [7:0] vlr;
    wire [7:0] tot;

    fsmaccumulator uut (.clk(clk), .rst(rst), .x(x), .vlr(vlr), .tot(tot));

    initial begin
        $dumpfile("main.vcd");
        $dumpvars(0, main_tb);
        clk = 0; vlr = 8'b0; x = 1'b0;
    end

    always #1 clk = ~clk;

    initial begin

        $monitor("CLK=%d, RST=%d, X=%d, ST=%d VLR=%d, TOT=%d", clk, rst, x, uut.state, vlr, tot);

        rst = 1'b0; #1 rst = 1'b1;
        x = 1'b0; vlr = 8'b1010; #2
        x = 1'b1; #2
        x = 1'b0; vlr = 8'b1010; #2
        x = 1'b1; #2
        
        // rst = 1'b0; #1 rst = 1'b1;
        x = 1'b0; vlr = 8'b1010; #2
        x = 1'b1; #2
        x = 1'b0; vlr = 8'b1010; #2
        x = 1'b1; #2

        $finish;

    end

endmodule

Verilog/FSM/Accumulator/main.vcd
$date
	Sat Jul  4 13:53:13 2026
$end
$version
	Icarus Verilog
$end
$timescale
	1s
$end
$scope module main_tb $end
$var wire 8 ! tot [7:0] $end
$var reg 1 " clk $end
$var reg 1 # rst $end
$var reg 8 $ vlr [7:0] $end
$var reg 1 % x $end
$scope module uut $end
$var wire 1 " clk $end
$var wire 1 # rst $end
$var wire 8 & vlr [7:0] $end
$var wire 1 % x $end
$var parameter 2 ' START $end
$var parameter 2 ( SUM $end
$var parameter 2 ) WAIT $end
$var parameter 2 * WAIT2 $end
$var reg 2 + state [1:0] $end
$var reg 8 , tot [7:0] $end
$upscope $end
$upscope $end
$enddefinitions $end
$comment Show the parameter values. $end
$dumpall
b11 *
b1 )
b10 (
b0 '
$end
#0
$dumpvars
b0 ,
b0 +
b0 &
0%
b0 $
0#
0"
b0 !
$end
#1
b1 +
b1010 $
b1010 &
1#
1"
#2
0"
#3
1"
1%
#4
0"
#5
b10 +
1"
0%
#6
0"
#7
b11 +
b1010 !
b1010 ,
1"
1%
#8
0"
#9
b1 +
1"
0%
#10
0"
#11
1"
1%
#12
0"
#13
b10 +
1"
0%
#14
0"
#15
b11 +
b10100 !
b10100 ,
1"
1%
