Sequential/ParallelLoad/main.v
module parallelload(clk, ld, d, q);
    input [3:0] d;
    input clk, ld;
    output reg [3:0] q;

    initial begin
        q = 4'b0000;
    end

    always @(negedge clk) begin
        if (ld == 1'b1)
            q <= d;
    end
endmodule

Verilog/Sequential/ParallelLoad/tb.v
module main_tb;

    reg [3:0] d;
    reg clk, ld;
    wire [3:0] q;

    parallelload uut (.d(d), .clk(clk), .ld(ld), .q(q));

    initial begin
        $dumpfile("main.vcd");
        $dumpvars(0, main_tb);
        clk = 1'b0; d = 4'b0000; ld = 1'b0;
    end

    initial begin
        $monitor("Input: %b | Output: %b | Time: %0t", d, q, $time);
        repeat(10) begin
            #10 d = d + 1; ld = ~ld;
        end
        $finish;
    end

    always #5 clk = ~clk;    

endmodule

Verilog/Sequential/ParallelLoad/main.vcd
$date
	Wed Jul  1 09:17:53 2026
$end
$version
	Icarus Verilog
$end
$timescale
	1s
$end
$scope module main_tb $end
$var wire 4 ! q [3:0] $end
$var reg 1 " clk $end
$var reg 4 # d [3:0] $end
$var reg 1 $ ld $end
$scope module uut $end
$var wire 1 " clk $end
$var wire 4 % d [3:0] $end
$var wire 1 $ ld $end
$var reg 4 & q [3:0] $end
$upscope $end
$upscope $end
$enddefinitions $end
#0
$dumpvars
b0 &
b0 %
0$
b0 #
0"
b0 !
$end
#5
1"
#10
b1 !
b1 &
0"
1$
b1 #
b1 %
#15
1"
#20
0"
0$
b10 #
b10 %
#25
1"
#30
b11 !
b11 &
0"
1$
b11 #
b11 %
#35
1"
#40
0"
0$
b100 #
b100 %
#45
1"
#50
b101 !
b101 &
0"
1$
b101 #
b101 %
#55
1"
#60
0"
0$
b110 #
b110 %
#65
1"
#70
b111 !
b111 &
0"
1$
b111 #
b111 %
#75
1"
#80
0"
0$
b1000 #
b1000 %
#85
1"
#90
b1001 !
b1001 &
0"
1$
b1001 #
b1001 %
#95
1"
#100
0"
0$
b1010 #
b1010 %
