Verilog/Combinational/Mux4x1/main.v
/*
 * Mux 4 x 1
 */
`default_nettype none
module mux4x1(i0, i1, i2, i3, s0, s1, f);

    input i0, i1, i2, i3, s0, s1;
    output f;

    assign f = i0 & ~s0 & ~s1 | i1 & ~s1 & s0 | i2 & s1 & ~s0 | i3 & s1 & s0;

endmodule

Combinational/Mux4x1/tb.v
module main_tb;

    reg i0, i1, i2, i3, s0, s1;
    wire f;

    mux4x1 uut(.i0(i0), .i1(i1), .i2(i2), .i3(i3), .s0(s0), .s1(s1), .f(f));

    initial begin
        $dumpfile("main.vcd");
        $dumpvars(0, main_tb);
    end

    initial begin
        $monitor("Time=%0dns | I0=%d | I1=%d | I2=%d | I3=%d | S0=%d | S1=%d | F=%d", $time, i0, i1, i2, i3, s0, s1, f);
        
        // Out I0
        s0 = 1'b0; s1 = 1'b0;
        i0 = 1'b1; i1 = 1'b0; i2 = 1'b0; i3 = 1'b0;
        #100
        i0 = 1'b0; i1 = 1'b0; i2 = 1'b0; i3 = 1'b0;
        #100

        // Out I1
        s0 = 1'b1; s1 = 1'b0;
        i0 = 1'b0; i1 = 1'b1; i2 = 1'b0; i3 = 1'b0;
        #100
        i0 = 1'b0; i1 = 1'b0; i2 = 1'b0; i3 = 1'b0;
        #100

        // Out I2
        s0 = 1'b0; s1 = 1'b1;
        i0 = 1'b0; i1 = 1'b0; i2 = 1'b1; i3 = 1'b0;
        #100
        i0 = 1'b0; i1 = 1'b0; i2 = 1'b0; i3 = 1'b0;
        #100
        
        // Out I3
        s0 = 1'b1; s1 = 1'b1;
        i0 = 1'b0; i1 = 1'b0; i2 = 1'b0; i3 = 1'b1;
        #100
        i0 = 1'b0; i1 = 1'b0; i2 = 1'b0; i3 = 1'b0;
        #100
        
        $finish;
    end

endmodule

Combinational/Mux4x1/main.vcd
$date
	Mon Jun 29 10:36:18 2026
$end
$version
	Icarus Verilog
$end
$timescale
	1s
$end
$scope module main_tb $end
$var wire 1 ! f $end
$var reg 1 " i0 $end
$var reg 1 # i1 $end
$var reg 1 $ i2 $end
$var reg 1 % i3 $end
$var reg 1 & s0 $end
$var reg 1 ' s1 $end
$scope module uut $end
$var wire 1 ! f $end
$var wire 1 " i0 $end
$var wire 1 # i1 $end
$var wire 1 $ i2 $end
$var wire 1 % i3 $end
$var wire 1 & s0 $end
$var wire 1 ' s1 $end
$upscope $end
$upscope $end
$enddefinitions $end
$comment Show the parameter values. $end
$dumpall
$end
#0
$dumpvars
0'
0&
0%
0$
0#
1"
1!
$end
#100
0!
0"
#200
1!
1#
1&
#300
0!
0#
#400
1!
1$
1'
0&
#500
0!
0$
#600
1!
1%
1&
#700
0!
0%
