Sequential/BCD7Seg/main.v
/*
 * BCD to 7-segment decoder (Common Anode)
 */
module bcd7seg(in, a, b, c, d, e, f, g);
    input [3:0] in;
    output reg a, b, c, d, e, f, g;

    always @* begin        
        case (in)
            4'b0000: {a, b, c, d, e, f, g} = 7'b0000001; // 0
            4'b0001: {a, b, c, d, e, f, g} = 7'b1001111; // 1
            4'b0010: {a, b, c, d, e, f, g} = 7'b0010010; // 2
            4'b0011: {a, b, c, d, e, f, g} = 7'b0000110; // 3
            4'b0100: {a, b, c, d, e, f, g} = 7'b1001100; // 4
            4'b0101: {a, b, c, d, e, f, g} = 7'b0100100; // 5
            4'b0110: {a, b, c, d, e, f, g} = 7'b0100000; // 6
            4'b0111: {a, b, c, d, e, f, g} = 7'b0001111; // 7
            4'b1000: {a, b, c, d, e, f, g} = 7'b0000000; // 8
            4'b1001: {a, b, c, d, e, f, g} = 7'b0000100; // 9
            default: {a, b, c, d, e, f, g} = 7'b1111111; // blank
        endcase    
    end
endmodule

Verilog/Sequential/BCD7Seg/tb.v
module main_tb;
    reg [3:0] in;
    wire a, b, c, d, e, f, g;

    initial begin
        $dumpfile("main.vcd");
        $dumpvars(0, main_tb);
    end

    bcd7seg uut(.in(in), .a(a), .b(b), .c(c), .d(d), .e(e), .f(f), .g(g));

    initial begin
        in = 4'b0000;
        // $monitor("Time: %0t | Input: %b | Output: a=%b b=%b c=%b d=%b e=%b f=%b g=%b", $time, in, a, b, c, d, e, f, g);
        $monitor("Input: %b | Output: a=%b b=%b c=%b d=%b e=%b f=%b g=%b | Time: %0t", in, a, b, c, d, e, f, g, $time);
        repeat(10) begin
            #10 in = in + 1;
        end
    end

endmodule

Verilog/Sequential/BCD7Seg/main.vcd
$date
	Wed Jul  1 08:54:41 2026
$end
$version
	Icarus Verilog
$end
$timescale
	1s
$end
$scope module main_tb $end
$var wire 1 ! g $end
$var wire 1 " f $end
$var wire 1 # e $end
$var wire 1 $ d $end
$var wire 1 % c $end
$var wire 1 & b $end
$var wire 1 ' a $end
$var reg 4 ( in [3:0] $end
$scope module uut $end
$var wire 4 ) in [3:0] $end
$var reg 1 ' a $end
$var reg 1 & b $end
$var reg 1 % c $end
$var reg 1 $ d $end
$var reg 1 # e $end
$var reg 1 " f $end
$var reg 1 ! g $end
$upscope $end
$upscope $end
$enddefinitions $end
#0
$dumpvars
b0 )
b0 (
0'
0&
0%
0$
0#
0"
1!
$end
#10
1'
1$
1#
1"
b1 (
b1 )
#20
0'
1%
0$
0#
0!
b10 (
b10 )
#30
0%
1#
b11 (
b11 )
#40
1'
1$
0"
b100 (
b100 )
#50
0'
1&
0$
b101 (
b101 )
#60
0#
b110 (
b110 )
#70
0&
1$
1#
1"
1!
b111 (
b111 )
#80
0$
0#
0"
0!
b1000 (
b1000 )
#90
1#
b1001 (
b1001 )
#100
1'
1&
1%
1$
1"
1!
b1010 (
b1010 )
