Verilog/FSM/MooreMachine/main.v
module fsmmoore(clk, rst, x, y);
    input clk, rst, x;
    output reg y;

    reg [1:0] state;

    localparam a = 2'b00,
               b = 2'b01,
               c = 2'b10,
               d = 2'b11;

    initial begin
        state <= a;
    end

    always @(negedge clk, negedge rst) begin
        if (rst == 1'b0) begin
            state <= a;
        end
        else begin
            case(state)
            a: begin
                if (x == 1'b0) state <= b;
                else state <= a;
             end
            b: begin
                if (x == 1'b0) state <= b;
                else state <= c;
             end
            c: begin
                state <= d;
            end
            d: begin
                state <= a;
            end
            endcase
        end
    end

    always @ (state) begin
        case (state)
        a: y = 1'b1;
        b: y = 1'b0;
        c: y = 1'b0;
        d: y = 1'b1;
        endcase
    end
endmodule

Verilog/FSM/MooreMachine/tb.v
module main_tb;
    reg clk, rst, x;
    wire y;

    fsmmoore uut(.clk(clk), .rst(rst), .x(x), .y(y));

    initial begin
        $dumpfile("main.vcd");
        $dumpvars(0, main_tb);
        clk = 0; x = 1;
    end

    always #5 clk = ~clk;

    initial begin
        $monitor ("RST=%d CLK=%d X=%d Y=%d ST=%d", rst, clk, x, y, uut.state);
        rst = 0; #5 rst = 1;
        x = 1;#5
        x = 0;#10
        x = 1;#30
        x = 0;#10
        x = 1;#5
        #20
        $finish;
    end

endmodule

Verilog/FSM/MealyMachine/main.vcd
$date
	Thu Jul  2 17:07:43 2026
$end
$version
	Icarus Verilog
$end
$timescale
	1s
$end
$scope module main_tb $end
$var wire 1 ! y $end
$var reg 1 " clk $end
$var reg 1 # rst $end
$var reg 1 $ x $end
$scope module uut $end
$var wire 1 " clk $end
$var wire 1 # rst $end
$var wire 1 $ x $end
$var reg 2 % state [1:0] $end
$var reg 1 ! y $end
$upscope $end
$upscope $end
$enddefinitions $end
#0
$dumpvars
b0 %
x$
0#
0"
0!
$end
#1
1$
1#
#5
1"
#10
b1 %
0"
#11
0$
#15
1"
#20
b10 %
0"
#21
1$
#25
1"
#30
b11 %
0"
#31
1!
0$
#35
1"
#40
0!
b10 %
0"
#41
b0 %
0#
#42
1$
1#
#45
1"
#50
b1 %
0"
#52
0$
#55
1"
#60
b10 %
0"
#62
1$
#65
1"
#70
b11 %
0"
#72
1!
0$
#75
1"
#80
0!
b10 %
0"
