Verilog/Sequential/FlipFlopReset/main.v
module dff (input wire clk, input wire d, input wire rst, output reg q);

always @(posedge clk)
begin
    if (rst)
        q <= 0;
    else
        q <= d;
end

endmodule

Sequential/FlipFlopReset/tb.v
`timescale 1ns/1ps

module dff_tb;

reg clk;
reg d;
wire q;
wire rst;

dff uut (.clk(clk), .d(d), .q(q), .rst(rst));

initial
begin
    $dumpfile("wave.vcd");
    $dumpvars(0, dff_tb);

    clk = 0;
    d = 0;

    #10 d = 1;
    #20 d = 0;
    #20 d = 1;
    #20 d = 0;

    #20 $finish;
end

always
begin
    #5 clk = ~clk;
end

endmodule

Sequential/FlipFlopReset/wave.vcd
$date
	Mon Jun 22 12:05:30 2026
$end
$version
	Icarus Verilog
$end
$timescale
	1ps
$end
$scope module dff_tb $end
$var wire 1 ! rst $end
$var wire 1 " q $end
$var reg 1 # clk $end
$var reg 1 $ d $end
$scope module uut $end
$var wire 1 # clk $end
$var wire 1 $ d $end
$var wire 1 ! rst $end
$var reg 1 " q $end
$upscope $end
$upscope $end
$enddefinitions $end
#0
$dumpvars
0$
0#
x"
z!
$end
#5000
0"
1#
#10000
0#
1$
#15000
1"
1#
#20000
0#
#25000
1#
#30000
0#
0$
#35000
0"
1#
#40000
0#
#45000
1#
#50000
0#
1$
#55000
1"
1#
#60000
0#
#65000
1#
#70000
0#
0$
#75000
0"
1#
