Sequential/Counter4Bit/main.v
module counter4Bit(clk, q);
    input clk;
    output reg [3:0] q;

    initial begin
        q = 4'b0000;
    end

    always @(posedge clk) begin
        q <= q + 4'b0001;
    end
endmodule

Sequential/Counter4Bit/tb.v
module main_tb;

    reg clk;
    wire [3:0] q;
    
    initial begin
        $dumpfile("main.vcd");
        $dumpvars(0, main_tb);
    end

    counter4Bit uut(.clk(clk), .q(q));

    initial begin
        clk = 0;
        repeat (16) @(posedge clk);
        $finish;
    end

    always #5 clk = ~clk;

    always @(posedge clk)
        $display("Time=%0t q=%b", $time, q);

endmodule

Sequential/Counter4Bit/main.vcd
$date
	Tue Jun 30 23:17:38 2026
$end
$version
	Icarus Verilog
$end
$timescale
	1s
$end
$scope module main_tb $end
$var wire 4 ! q [3:0] $end
$var reg 1 " clk $end
$scope module uut $end
$var wire 1 " clk $end
$var reg 4 # q [3:0] $end
$upscope $end
$upscope $end
$enddefinitions $end
$comment Show the parameter values. $end
$dumpall
$end
#0
$dumpvars
b0 #
0"
b0 !
$end
#5
b1 !
b1 #
1"
#10
0"
#15
b10 !
b10 #
1"
#20
0"
#25
b11 !
b11 #
1"
#30
0"
#35
b100 !
b100 #
1"
#40
0"
#45
b101 !
b101 #
1"
#50
0"
#55
b110 !
b110 #
1"
#60
0"
#65
b111 !
b111 #
1"
#70
0"
#75
b1000 !
b1000 #
1"
#80
0"
#85
b1001 !
b1001 #
1"
#90
0"
#95
b1010 !
b1010 #
1"
#100
0"
#105
b1011 !
b1011 #
1"
#110
0"
#115
b1100 !
b1100 #
1"
#120
0"
#125
b1101 !
b1101 #
1"
#130
0"
#135
b1110 !
b1110 #
1"
#140
0"
#145
b1111 !
b1111 #
1"
#150
0"
#155
b0 !
b0 #
1"
